app_common_python/__init__.py
app_common_python/types.py
app_common_python-0.2.9.dist-info/METADATA
app_common_python-0.2.9.dist-info/WHEEL
app_common_python-0.2.9.dist-info/top_level.txt
app_common_python-0.2.9.dist-info/RECORD
