Metadata-Version: 2.4
Name: app-common-python
Version: 0.2.9
Home-page: https://github.com/RedHatInsights/app-common-python
Author-email: psavage@redhat.com
